{
  "tasks": {
    "dev": "deno run --allow-net --allow-read --allow-write --allow-env --allow-sys --watch api/main.ts",
    "start": "cd webapp && npx ng serve --proxy-config proxy.conf.json",
    "test": "cd webapp && npx ng test --browsers ChromeHeadless --code-coverage true --watch false"
  },
  "imports": {
    "@db/mongo": "jsr:@db/mongo@^0.34.0",
    "@oak/oak": "jsr:@oak/oak@^17.1.4",
    "@std/dotenv": "jsr:@std/dotenv@^0.225.5",
    "@std/path": "jsr:@std/path@^1.1.0"
  },
  "compilerOptions": {
    "strict": true
  },
  "exclude": ["webapp/"]
}
